setup.cfg
setup.py
graphcreator/__init__.py
graphcreator/constants.py
graphcreator/exceptions.py
graphcreator/graph.py
graphcreator/graphcreator.py
graphcreator/iofile.py
graphcreator/properties.py
graphcreator.egg-info/PKG-INFO
graphcreator.egg-info/SOURCES.txt
graphcreator.egg-info/dependency_links.txt
graphcreator.egg-info/requires.txt
graphcreator.egg-info/top_level.txt