Metadata-Version: 2.1
Name: graphcreator
Version: 1.1.1.5
Summary: Python module for creating graphs using files
Home-page: https://github.com/FranChesK0/GraphCreator
Author: FranChesKo
Author-email: khl_doss@mail.ru
License: Apache License, Version 2.0, see LICENSE file
Download-URL: https://github.com/FranChesK0/GraphCreator/archive/v1.1.1.5
Platform: UNKNOWN
Classifier: License :: OSI Approved :: Apache Software License
Classifier: Operating System :: OS Independent
Classifier: Intended Audience :: Developers
Classifier: Programming Language :: Python
Classifier: Programming Language :: Python :: 3
Classifier: Programming Language :: Python :: 3.9
Classifier: Programming Language :: Python :: 3.10
Classifier: Programming Language :: Python :: Implementation :: PyPy
Classifier: Programming Language :: Python :: Implementation :: CPython
